ef_ppo/__init__.py
ef_ppo/critics.py
ef_ppo/ef_ppo.py
ef_ppo/ef_ppo_trainer.py
ef_ppo/hl_segment.py
ef_ppo/models.py
ef_ppo/test_environment.py
ef_ppo/utils.py
ef_ppo-0.1.1.dist-info/METADATA
ef_ppo-0.1.1.dist-info/WHEEL
ef_ppo-0.1.1.dist-info/RECORD
